python_cyber/__init__.py
python_cyber/cyber.py
python_cyber/cyber_time.py
python_cyber/cyber_timer.py
python_cyber/parameter.py
python_cyber/record.py
python_cyber/conf/compute_sched.conf
python_cyber/conf/compute_sched_choreography.conf
python_cyber/conf/compute_sched_classic.conf
python_cyber/conf/control_sched.conf
python_cyber/conf/control_sched_choreography.conf
python_cyber/conf/control_sched_classic.conf
python_cyber/conf/cyber.pb.conf
python_cyber/conf/dreamview_sched.conf
python_cyber/examples/__init__.py
python_cyber/examples/client.py
python_cyber/examples/listener.py
python_cyber/examples/parameter.py
python_cyber/examples/record.py
python_cyber/examples/record_channel_info.py
python_cyber/examples/record_trans.py
python_cyber/examples/service.py
python_cyber/examples/talker.py
python_cyber/examples/time.py
python_cyber/examples/timer.py
python_cyber/internal/_cyber_parameter_wrapper.so
python_cyber/internal/_cyber_record_wrapper.so
python_cyber/internal/_cyber_time_wrapper.so
python_cyber/internal/_cyber_wrapper.so
python_cyber/internal/cyber_monitor
python_cyber/internal/cyber_recorder
python_cyber/internal/cyber_recorder_old
python_cyber/internal/libPocoFoundation.so.94
python_cyber/internal/libcyber.so
python_cyber/internal/libfastcdr.so.1
python_cyber/internal/libfastrtps.so.1
python_cyber/internal/libgflags.so.2.2
python_cyber/internal/libglog.so.0
python_cyber/internal/libprotobuf.so.3.14.0.0
python_cyber/internal/libuuid.so.1
python_cyber/proto/__init__.py
python_cyber/proto/choreography_conf_pb2.py
python_cyber/proto/classic_conf_pb2.py
python_cyber/proto/clock_pb2.py
python_cyber/proto/component_conf_pb2.py
python_cyber/proto/cyber_conf_pb2.py
python_cyber/proto/dag_conf_pb2.py
python_cyber/proto/parameter_pb2.py
python_cyber/proto/perf_conf_pb2.py
python_cyber/proto/proto_desc_pb2.py
python_cyber/proto/qos_profile_pb2.py
python_cyber/proto/record_pb2.py
python_cyber/proto/role_attributes_pb2.py
python_cyber/proto/run_mode_conf_pb2.py
python_cyber-0.0.5.dist-info/LICENSE
python_cyber-0.0.5.dist-info/METADATA
python_cyber-0.0.5.dist-info/WHEEL
python_cyber-0.0.5.dist-info/entry_points.txt
python_cyber-0.0.5.dist-info/top_level.txt
python_cyber-0.0.5.dist-info/RECORD
