Metadata-Version: 2.1
Name: python_cyber
Version: 0.0.5
Summary: cyber python wrapper
Home-page: https://github.com/daohu527/python_cyber
Author: liufei
Author-email: 1373945731liufei@gmail.com
Project-URL: Bug Tracker, https://github.com/daohu527/python_cyber/issues
Classifier: Programming Language :: Python :: 3
Classifier: License :: OSI Approved :: Apache Software License
Classifier: Operating System :: OS Independent
Requires-Python: >=3.8
License-File: LICENSE
Requires-Dist: protobuf >=3.14.0
